[
  {
    "seed": "피부건강",
    "group": "여성·중장년 건강",
    "keyword": "히알루론산",
    "title": "히알루론산 효능과 부작용 총정리: 피부·관절·눈 건강 관리법 2026",
    "url": "https://healthier-sam.blogspot.com/2026/07/2026_01714629326.html",
    "monthly_searches": 38100,
    "published_at": "2026-07-18T11:05:04.295442"
  },
  {
    "seed": "지방간",
    "group": "만성질환 관리",
    "keyword": "갑상선기능저하증",
    "title": "갑상선기능저하증 초기증상부터 치료까지 완벽 가이드 2026",
    "url": "https://healthier-sam.blogspot.com/2026/07/2026_0939581547.html",
    "monthly_searches": 59510,
    "published_at": "2026-07-18T23:58:58.779648"
  }
]